gettake/__init__.py
gettake/gettake.py
gettake/main.py
gettake/models.py
gettake/py.typed
gettake-0.3.0.dist-info/METADATA
gettake-0.3.0.dist-info/WHEEL
gettake-0.3.0.dist-info/entry_points.txt
gettake-0.3.0.dist-info/licenses/LICENSE.txt
gettake-0.3.0.dist-info/RECORD
