Metadata-Version: 2.4
Name: gettake
Version: 0.3.0
Summary: Get and save images from webcomicgamma
Project-URL: Documentation, https://egpl.dev/gettake/
Project-URL: Repository, https://github.com/eggplants/gettake
Author-email: eggplants <w10776e8w@yahoo.co.jp>
License: MIT
License-File: LICENSE.txt
Keywords: cli,downloader,manga
Classifier: License :: OSI Approved :: MIT License
Classifier: Programming Language :: Python :: 3 :: Only
Classifier: Programming Language :: Python :: 3.10
Classifier: Programming Language :: Python :: 3.11
Classifier: Programming Language :: Python :: 3.12
Classifier: Programming Language :: Python :: 3.13
Classifier: Programming Language :: Python :: 3.14
Classifier: Topic :: Multimedia :: Graphics
Classifier: Typing :: Typed
Requires-Python: <4,>=3.10
Requires-Dist: pillow<12,>=11.1
Requires-Dist: requests<3,>=2.32.3
